sqlite3_to_mysql/__init__.py
sqlite3_to_mysql/cli.py
sqlite3_to_mysql/click_utils.py
sqlite3_to_mysql/debug_info.py
sqlite3_to_mysql/mysql_utils.py
sqlite3_to_mysql/py.typed
sqlite3_to_mysql/sqlite_utils.py
sqlite3_to_mysql/transporter.py
sqlite3_to_mysql/types.py
sqlite3_to_mysql-2.5.5.dist-info/METADATA
sqlite3_to_mysql-2.5.5.dist-info/WHEEL
sqlite3_to_mysql-2.5.5.dist-info/entry_points.txt
sqlite3_to_mysql-2.5.5.dist-info/licenses/LICENSE
sqlite3_to_mysql-2.5.5.dist-info/RECORD
